cariutils/__init__.py
cariutils/basetest.py
cariutils/cli.py
cariutils/itertools.py
cariutils/jsonschema.py
cariutils/mock.py
cariutils/release.py
cariutils/settings.py
cariutils/shortcuts.py
cariutils/typing.py
cariutils/wait.py
cariutils-1.15.0.dist-info/LICENSE
cariutils-1.15.0.dist-info/METADATA
cariutils-1.15.0.dist-info/WHEEL
cariutils-1.15.0.dist-info/entry_points.txt
cariutils-1.15.0.dist-info/RECORD
