Metadata-Version: 2.1
Name: cariutils
Version: 1.15.0
Summary: Carium Utility Library
Author: Carium Devops
Author-email: devops@carium.com
Requires-Python: >=3.10,<4.0
Classifier: Programming Language :: Python :: 3
Classifier: Programming Language :: Python :: 3.10
Classifier: Programming Language :: Python :: 3.11
Classifier: Programming Language :: Python :: 3.12
Requires-Dist: GitPython
Requires-Dist: PyGithub
Requires-Dist: bump2version
Requires-Dist: jsonschema
Requires-Dist: python-dateutil
Requires-Dist: requests
Requires-Dist: tenacity
